Metadata-Version: 1.1
Name: cexio
Version: 0.1.9
Summary: Python wrapper for CEX.IO
Home-page: https://github.com/fasetto/python-cexio
Author: fasetto
Author-email: serkanbircan21@yandex.com
License: MIT
Platform: UNKNOWN
Classifier: Programming Language :: Python
Classifier: Programming Language :: Python :: 3.5
Classifier: Operating System :: OS Independent
Classifier: License :: OSI Approved :: MIT License
Classifier: Development Status :: 3 - Alpha
Classifier: Topic :: Office/Business :: Financial
